ovos_ocp_files_plugin/__about__.py
ovos_ocp_files_plugin/__init__.py
ovos_ocp_files_plugin/api.py
ovos_ocp_files_plugin/config.py
ovos_ocp_files_plugin/exceptions.py
ovos_ocp_files_plugin/models.py
ovos_ocp_files_plugin/plugin.py
ovos_ocp_files_plugin/utils.py
ovos_ocp_files_plugin/version.py
ovos_ocp_files_plugin/formats/__init__.py
ovos_ocp_files_plugin/formats/flac.py
ovos_ocp_files_plugin/formats/id3v1.py
ovos_ocp_files_plugin/formats/id3v2.py
ovos_ocp_files_plugin/formats/id3v2frames.py
ovos_ocp_files_plugin/formats/mp3.py
ovos_ocp_files_plugin/formats/mp4.py
ovos_ocp_files_plugin/formats/mp4_tags.py
ovos_ocp_files_plugin/formats/ogg.py
ovos_ocp_files_plugin/formats/oggopus.py
ovos_ocp_files_plugin/formats/oggvorbis.py
ovos_ocp_files_plugin/formats/tables.py
ovos_ocp_files_plugin/formats/vorbiscomments.py
ovos_ocp_files_plugin/formats/wave.py
ovos_ocp_files_plugin/tbm_utils/__init__.py
ovos_ocp_files_plugin/tbm_utils/decorators.py
ovos_ocp_files_plugin/tbm_utils/humanize.py
ovos_ocp_files_plugin/tbm_utils/io.py
ovos_ocp_files_plugin/tbm_utils/structures.py
ovos_ocp_files_plugin-0.13.1.dist-info/LICENSE
ovos_ocp_files_plugin-0.13.1.dist-info/METADATA
ovos_ocp_files_plugin-0.13.1.dist-info/WHEEL
ovos_ocp_files_plugin-0.13.1.dist-info/entry_points.txt
ovos_ocp_files_plugin-0.13.1.dist-info/top_level.txt
ovos_ocp_files_plugin-0.13.1.dist-info/zip-safe
ovos_ocp_files_plugin-0.13.1.dist-info/RECORD
